MANIFEST.in
README.rst
requirements.txt
setup.py
bin/ino
ino/__init__.py
ino/argparsing.py
ino/conf.py
ino/environment.py
ino/exc.py
ino/filters.py
ino/runner.py
ino/utils.py
ino.egg-info/PKG-INFO
ino.egg-info/SOURCES.txt
ino.egg-info/dependency_links.txt
ino.egg-info/requires.txt
ino.egg-info/top_level.txt
ino/commands/__init__.py
ino/commands/base.py
ino/commands/build.py
ino/commands/clean.py
ino/commands/init.py
ino/commands/listmodels.py
ino/commands/preproc.py
ino/commands/serial.py
ino/commands/upload.py
ino/make/Makefile.common.jinja
ino/make/Makefile.deps.jinja
ino/make/Makefile.jinja
ino/make/Makefile.sketch.jinja
ino/templates/blink/manifest.ini
ino/templates/blink/lib/.holder
ino/templates/blink/src/sketch.ino
ino/templates/empty/manifest.ini
ino/templates/empty/lib/.holder
ino/templates/empty/src/sketch.ino