Metadata-Version: 1.0
Name: ino
Version: 0.3.3
Summary: Command line toolkit for working with Arduino hardware
Home-page: http://inotool.org
Author: Victor Nakoryakov, Amperka Team
Author-email: victor@amperka.ru
License: MIT
Keywords: arduino build system
Platform: UNKNOWN
Classifier: Development Status :: 4 - Beta
Classifier: License :: OSI Approved :: MIT License
Classifier: Intended Audience :: Developers
Classifier: Operating System :: OS Independent
Classifier: Programming Language :: Python
Classifier: Topic :: Software Development :: Embedded Systems
